youtube_transcript_downloader/__init__.py
youtube_transcript_downloader/yt_transcript_downloader.py
youtube_transcript_downloader-0.1.2.dist-info/LICENSE
youtube_transcript_downloader-0.1.2.dist-info/METADATA
youtube_transcript_downloader-0.1.2.dist-info/WHEEL
youtube_transcript_downloader-0.1.2.dist-info/top_level.txt
youtube_transcript_downloader-0.1.2.dist-info/RECORD
