Metadata-Version: 2.1
Name: youtube-transcript-downloader
Version: 0.1.2
Summary: A package for retrieving transcripts from youtube
Home-page: https://github.com/t4skmanag3r/youtube_transcript_downloader
Author: Edvinas Adomaitis
Author-email: edvinasad7@gmail.com
License: UNKNOWN
Platform: UNKNOWN
Classifier: Development Status :: 3 - Alpha
Classifier: Intended Audience :: Developers
Classifier: Programming Language :: Python :: 3
Classifier: License :: OSI Approved :: MIT License
Classifier: Operating System :: OS Independent
Requires-Python: >=3.8.5
